plbtc/__init__.py
plbtc/base58.py
plbtc/bech32.py
plbtc/config.py
plbtc/core.py
plbtc/denomination.py
plbtc/ecdsa.py
plbtc/opcode.py
plbtc/ripemd160.py
plbtc/rpc.py
plbtc/schnorr.py
plbtc/secp256k1.py
plbtc/wallet.py
plbtc-1.2.1.dist-info/METADATA
plbtc-1.2.1.dist-info/WHEEL
plbtc-1.2.1.dist-info/licenses/LICENSE
plbtc-1.2.1.dist-info/RECORD
