Metadata-Version: 2.3
Name: plbtc
Version: 1.2.1
Summary: Plbtc: bitcoin library for humans
Project-URL: homepage, https://github.com/mohanson/plbtc
Author-email: Mohanson <mohanson@outlook.com>
License: MIT License
Requires-Dist: requests
